<?xml version="1.0"?>
<!-- This file is part of the book                 -->
<!--                                               -->
<!--   Abstract Algebra: Theory and Applications   -->
<!--                                               -->
<!-- Copyright (C) 1997-2014  Thomas W. Judson     -->
<!-- See the file COPYING for copying conditions.  -->
<!--                                               -->
<!-- This file is automatically generated from the -->
<!-- private solution manual.  Minor contributed   -->
<!-- edits can be made against this file for       -->
<!-- the purpose of a pull request.                -->
<exercises xml:id="exercises-fields">
	<title>Ejercicios</title>

	<exercise number="1">
		<statement>
			<p>Muestre que cada uno de los siguientes números es algebraico sobre <m>{\mathbb Q}</m> encontrando su polinomio minimal sobre <m>{\mathbb Q}</m>.
				<ol>

					<li><p><m>\sqrt{ 1/3 + \sqrt{7} }</m></p></li>

					<li><p><m>\sqrt{ 3} + \sqrt[3]{5}</m></p></li>

					<li><p><m>\sqrt{3} + \sqrt{2}\, i</m></p></li>

					<li><p><m>\cos \theta + i \sin \theta</m> para <m>\theta = 2 \pi /n</m> con <m>n \in {\mathbb N}</m></p></li>

					<li><p><m>\sqrt{ \sqrt[3]{2} - i }</m></p></li>

				</ol></p>
		</statement>
		<hint>
			<p>(a) <m>x^4 - (2/3) x^2 - 62/9</m>; (c) <m>x^4 - 2 x^2 + 25</m>.</p>
		</hint>
		
	</exercise>

	<exercise number="2">
		<statement>
		<p>Encuentre una base para cada una de las siguientes extensiones de cuerpos. ¿Cuál es el grado de esta extensión?
			<ol>
			 
				<li><p><m>{\mathbb Q}( \sqrt{3}, \sqrt{6}\, )</m> sobre <m>{\mathbb Q}</m></p></li>
				 
				<li><p><m>{\mathbb Q}( \sqrt[3]{2}, \sqrt[3]{3}\, )</m> sobre <m>{\mathbb Q}</m></p></li>

				<li><p><m>{\mathbb Q}( \sqrt{2}, i)</m> sobre <m>{\mathbb Q}</m></p></li>

				<li><p><m>{\mathbb Q}( \sqrt{3}, \sqrt{5}, \sqrt{7}\, )</m> sobre <m>{\mathbb Q}</m></p></li>
				 
				<li><p><m>{\mathbb Q}( \sqrt{2}, \root 3 \of{2}\, )</m> sobre <m>{\mathbb Q}</m></p></li>

				<li><p><m>{\mathbb Q}( \sqrt{8}\, )</m> sobre <m>{\mathbb Q}(\sqrt{2}\, )</m></p></li>

				<li><p><m>{\mathbb Q}(i, \sqrt{2} +i, \sqrt{3} + i )</m> sobre <m>{\mathbb Q}</m></p></li>

				<li><p><m>{\mathbb Q}( \sqrt{2} + \sqrt{5}\, )</m> sobre <m>{\mathbb Q} ( \sqrt{5}\, )</m></p></li>

				<li><p><m>{\mathbb Q}( \sqrt{2}, \sqrt{6} + \sqrt{10}\, )</m> sobre <m>{\mathbb Q} ( \sqrt{3} + \sqrt{5}\, )</m></p></li>

			</ol></p>
		</statement>
		<hint>
			<p>(a) <m>\{ 1, \sqrt{2}, \sqrt{3}, \sqrt{6}\, \}</m>; (c) <m>\{ 1, i, \sqrt{2}, \sqrt{2}\, i \}</m>; (e) <m>\{1, 2^{1/6}, 2^{1/3}, 2^{1/2}, 2^{2/3}, 2^{5/6}  \}</m>.</p>
		</hint>
		
	</exercise>

	<exercise number="3">
		<statement>
			<p>Encuentre el cuerpo de descomposición de cada uno de los siguientes polinomios.
				<ol cols="2">

					<li><p><m>x^4 - 10 x^2 + 21</m> sobre <m>{\mathbb Q}</m></p></li>

					<li><p><m>x^4 + 1</m> sobre <m>{\mathbb Q}</m></p></li>

					<li><p><m>x^3 + 2x + 2</m> sobre <m>{\mathbb Z}_3</m></p></li>

					<li><p><m>x^3 - 3</m> sobre <m>{\mathbb Q}</m></p></li>

				</ol></p>
		</statement>
		<hint>
			<p>(a) <m>{\mathbb Q}(\sqrt{3}, \sqrt{7}\, )</m>.</p>
		</hint>
		
	</exercise>

	<exercise number="4">
		<statement>
			<p>Considere el cuerpo de extensión <m>{\mathbb Q}( \sqrt[4]{3}, i )</m> sobre <m>\mathbb Q</m>.
				<ol>

					<li><p>Encuentre una base para el cuerpo de extensión <m>{\mathbb Q}( \sqrt[4]{3}, i )</m> sobre <m>\mathbb Q</m>. Concluya que <m>[{\mathbb Q}( \sqrt[4]{3}, i ): \mathbb Q] = 8</m>.</p></li>

					<li><p>Encuentre todos los subcuerpos  <m>F</m> de <m>{\mathbb Q}( \sqrt[4]{3}, i )</m> tal que <m>[F:\mathbb Q] = 2</m>.</p></li>

					<li><p>Encuentre todos los subcuerpos <m>F</m> de <m>{\mathbb Q}( \sqrt[4]{3}, i )</m> tal que <m>[F:\mathbb Q] = 4</m>.</p></li>

				</ol></p>
		</statement>
		
	</exercise>

	<exercise number="5">
		<statement>
			<p>Demuestre que <m>{\mathbb Z}_2[x] / \langle x^3 + x + 1 \rangle</m> es un cuerpo con 8 elementos. Construya una tabla de multiplicación para el grupo multiplicativo del cuerpo.</p>
		</statement>
		<hint>
			<p>Use el hecho de que los elementos de <m>{\mathbb Z}_2[x]/ \langle x^3 + x + 1 \rangle</m> son 0, 1, <m>\alpha</m>, <m>1 + \alpha</m>, <m>\alpha^2</m>, <m>1 + \alpha^2</m>, <m>\alpha + \alpha^2</m>, <m>1 + \alpha + \alpha^2</m> y el hecho de que <m>\alpha^3 + \alpha + 1 = 0</m>.</p>
		</hint>
		
	</exercise>

	<exercise number="6">
		<statement>
			<p>Demuestre que el polígono regular de 9 lados no es constructible con regla y compas, pero el de 20 lados sí es constructible.</p>
		</statement>
		
	</exercise>

	<exercise number="7">
		<statement>
			<p>Demuestre que el coseno de un grado (<m>\cos 1^\circ</m>) es algebraico sobre <m>{\mathbb Q}</m> pero no es constructible.</p>
		</statement>
		
	</exercise>

	<exercise number="8">
		<statement>
			<p>¿Se puede construir un cubo con tres veces el volumen de un cubo dado?</p>
		</statement>
		<hint>
			<p>False.</p>
		</hint>
		
	</exercise>

	<exercise number="9">
		<statement>
			<p>Demuestre que <m>{\mathbb Q}(\sqrt{3}, \sqrt[4]{3}, \sqrt[8]{3}, \ldots )</m> es una extensión algebraica de <m>{\mathbb Q}</m> pero no es una extensión finita.</p>
		</statement>
		
	</exercise>

	<exercise number="10">
		<statement>
			<p>Demuestre o refute: <m>\pi</m> es algebraico sobre <m>{\mathbb Q}(\pi^3)</m>.</p>
		</statement>
		
	</exercise>

	<exercise number="11">
		<statement>
			<p>Sea <m>p(x)</m> un polinomio no constante de grado  <m>n</m> en <m>F[x]</m>. Demuestre que existe un cuerpo de descomposición  <m>E</m> para <m>p(x)</m> tal que <m>[E : F] \leq n!</m>.</p>
		</statement>
		
	</exercise>

	<exercise number="12">
		<statement>
			<p>Demuestre o refute: <m>{\mathbb Q}( \sqrt{2}\, ) \cong {\mathbb Q}( \sqrt{3}\, )</m>.</p>
		</statement>
		
	</exercise>

	<exercise number="13">
		<statement>
			<p>Demuestre que los cuerpos <m>{\mathbb Q}(\sqrt[4]{3}\, )</m> y <m>{\mathbb Q}(\sqrt[4]{3}\, i)</m> son isomorfos pero no iguales.</p>
		</statement>
		
	</exercise>

	<todo>Termine la demostración.</todo>

	<exercise number="14">
		<statement>
			<p>Sea <m>K</m> una extensión algebraica de <m>E</m>, y <m>E</m> una extensión algebraica de <m>F</m>. Demuestre que <m>K</m> es algebraico sobre <m>F</m>. [<em> Cuidado</em>: No suponga que las extensiones son finitas.]</p>
		</statement>
		<hint>
			<p>Supongamos que <m>E</m> es algebraico sobre <m>F</m> y <m>K</m> es algebraico sobre <m>E</m>. Sea <m>\alpha \in K</m>. Basta con demostrar que <m>\alpha</m> es algebraico sobre alguna extensión finita de <m>F</m>. Como <m>\alpha</m> es algebraico sobre <m>E</m>, debe ser cero de algún polinomio <m>p(x) = \beta_0 + \beta_1 x + \cdots + \beta_n x^n</m> en <m>E[x]</m>. Por lo tanto <m>\alpha</m> es algebraico sobre <m>F(\beta_0, \ldots, \beta_n)</m>.</p>
		</hint>
		
	</exercise>

	<exercise number="15">
		<statement>
			<p>Demuestre o refute: <m>{\mathbb Z}[x] / \langle x^3 -2 \rangle</m> es un cuerpo.</p>
		</statement>
		
	</exercise>

	<todo>Termine la demostración.</todo>

	<exercise number="16">
		<statement>
			<p>Sea <m>F</m> un cuerpo de característica <m>p</m>. Demuestre que <m>p(x) = x^p - a</m> es irreducible o se descompone completamente en <m>F</m>.</p>
		</statement>
		
	</exercise>

	<todo>Termine la demostración.</todo>

	<exercise number="17">
		<statement>
			<p>Sea <m>E</m> la clausura algebraica de un cuerpo <m>F</m>. Demuestre que todo polinomio <m>p(x)</m> en <m>F[x]</m> se descompone completamente en <m>E</m>.</p>
		</statement>
		
	</exercise>

	<exercise number="18">
		<statement>
			<p>Si todo polinomio irreducible <m>p(x)</m> en <m>F[x]</m> es lineal, demuestre que <m>F</m> es un cuerpo algebraicamente cerrado.</p>
		</statement>
		
	</exercise>

	<todo>Arregle la demostración.</todo>

	<exercise number="19">
		<statement>
			<p>Demuestre que si <m>\alpha</m> y <m>\beta</m> son números constructibles tales que <m>\beta \neq 0</m>, entonces también lo es <m>\alpha / \beta</m>.</p>
		</statement>
		
	</exercise>

	<todo>Arregle la demostración.</todo>

	<exercise number="20">
		<statement>
			<p>Demuestre que el conjunto de todos los elementos en <m>{\mathbb R}</m> que son algebraicos sobre <m>{\mathbb Q}</m> forma una extensión de cuerpos de <m>{\mathbb Q}</m> que no es finita.</p>
		</statement>
		
	</exercise>

	<exercise number="21">
		<statement>
			<p>Sea <m>E</m> una extensión algebraica de un cuerpo <m>F</m>, y sea <m>\sigma</m> un automorfismo de <m>E</m> que fija <m>F</m>. Sea <m>\alpha \in E</m>. Demuestre que <m>\sigma</m> induce una permutación del conjunto de ceros del polinomio minimal de <m>\alpha</m> que están en <m>E</m>.</p>
		</statement>
		
	</exercise>

	<exercise number="22">
		<statement>
			<p>Muestre que <m>{\mathbb Q}( \sqrt{3}, \sqrt{7}\, ) = {\mathbb Q}( \sqrt{3} + \sqrt{7}\, )</m>.  Extienda su demostración para demostrar que <m>{\mathbb Q}( \sqrt{a}, \sqrt{b}\, ) = {\mathbb Q}( \sqrt{a} + \sqrt{b}\, )</m>, donde <m>\gcd(a, b) = 1</m>.</p>
		</statement>
		<hint>
			<p>Como <m>\{ 1, \sqrt{3}, \sqrt{7}, \sqrt{21}\, \}</m> es una base para <m>{\mathbb Q}( \sqrt{3}, \sqrt{7}\, )</m> sobre <m>{\mathbb Q}</m>, <m>{\mathbb Q}( \sqrt{3}, \sqrt{7}\, ) \supset {\mathbb Q}( \sqrt{3} +\sqrt{7}\, )</m>. Como <m>[{\mathbb Q}( \sqrt{3}, \sqrt{7}\, ) : {\mathbb Q}] = 4</m>, <m>[{\mathbb Q}( \sqrt{3} + \sqrt{7}\, ) : {\mathbb Q}] = 2</m> o 4. Como el grado del polinomio minimal de <m>\sqrt{3} +\sqrt{7}</m> es 4, <m>{\mathbb Q}( \sqrt{3}, \sqrt{7}\, ) = {\mathbb Q}( \sqrt{3} +\sqrt{7}\, )</m>.</p>
		</hint>
		
	</exercise>

	<todo>Termine la demostración.</todo>

	<exercise number="23">
		<statement>
			<p>Sea <m>E</m> una extensión finita de un cuerpo <m>F</m>. Si <m>[E:F] = 2</m>, demuestre que  <m>E</m> es un cuerpo de descomposición sobre  <m>F</m> para algún polinomio <m>f(x) \in F[x]</m>.</p>
		</statement>
		
	</exercise>

	<exercise number="24">
		<statement>
			<p>Demuestre o refute: Dado un polinomio <m>p(x)</m> en <m>{\mathbb Z}_6[x]</m>, es posible construir un anillo <m>R</m> tal que <m>p(x)</m> tiene una raíz en <m>R</m>.</p>
		</statement>
		
	</exercise>

	<todo>Termine la demostración.</todo>

	<exercise number="25">
		<statement>
			<p>Sea <m>E</m> una extensión de <m>F</m> y <m>\alpha \in E</m>.  Determine <m>[F(\alpha): F(\alpha^3)]</m>.</p>
		</statement>
		
	</exercise>

	<todo>Termine la demostración.</todo>

	<exercise number="26">
		<statement>
			<p>Sean <m>\alpha, \beta</m> trascendente sobre <m>{\mathbb Q}</m>. Pruebe que al menos uno de <m>\alpha \beta</m> y <m>\alpha + \beta</m> también es trascendente.</p>
		</statement>
		
	</exercise>

	<exercise number="27">
		<statement>
			<p>Sea <m>E</m> una extensión de cuerpos de <m>F</m> y sea <m>\alpha \in E</m> trascendente sobre <m>F</m>. Demuestre que cada elemento en <m>F(\alpha)</m> que no está en  <m>F</m> también es trascendente sobre <m>F</m>.</p>
		</statement>
		<hint>
			<p>Sea <m>\beta \in F(\alpha)</m> no en <m>F</m>. Entonces <m>\beta = p(\alpha)/q(\alpha)</m>, donde <m>p</m> y <m>q</m> son polinomios en <m>\alpha</m> con <m>q(\alpha) \neq 0</m> y coeficientes en <m>F</m>. Si <m>\beta</m> es algebraico sobre <m>F</m>, entonces hay un polinomio <m>f(x) \in F[x]</m> tal que <m>f(\beta) = 0</m>. Sea <m>f(x) = a_0 + a_1 x + \cdots + a_n x^n</m>. Entonces 
				<me>0 = f(\beta) = f\left( \frac{p(\alpha)}{q(\alpha)} \right) = a_0 + a_1 \left( \frac{p(\alpha)}{q(\alpha)} \right)  + \cdots + a_n \left( \frac{p(\alpha)}{q(\alpha)} \right)^n.</me>
			Ahora multiplique ambos lados por <m>q(\alpha)^n</m> para demostrar que hay un polinomio en <m>F[x]</m> que se anula en <m>\alpha</m>.</p>
		</hint>
		
	</exercise>

	<exercise number="28" xml:id="exercise-fields-degree-irred-poly">
		<statement>
			<p>Sea <m>\alpha</m> una raíz de un polinomio irreducible <m>p(x) \in F[x]</m>, con <m>\deg p = n</m>. Demuestre que <m>[F(\alpha) : F] = n</m>.</p>
		</statement>
		<hint>
			<p>Vea el comentario que sigue al Teorema<nbsp/><xref ref="theorem-simple_extension"/>.</p>
		</hint>
		
	</exercise>

</exercises>
