<?xml version="1.0"?>
<!-- This file is part of the book                 -->
<!--                                               -->
<!--   Abstract Algebra: Theory and Applications   -->
<!--                                               -->
<!-- Copyright (C) 1997-2014  Thomas W. Judson     -->
<!-- See the file COPYING for copying conditions.  -->
<!--                                               -->
<!-- This file is automatically generated from the -->
<!-- private solution manual.  Minor contributed   -->
<!-- edits can be made against this file for       -->
<!-- the purpose of a pull request.                -->
<exercises xml:id="exercises-vect">
	<title>Ejercicios</title>

	<exercise number="1">
		<statement>
			<p>Si <m>F</m> es un cuerpo, muestre que <m>F[x]</m> es un espacio vectorial sobre <m>F</m>, donde los vectores en <m>F[x]</m> son polinomios. La suma de vectores es la suma de polinomios, y la multiplicación por escalar está definida por <m>\alpha p(x)</m> para <m>\alpha \in F</m>.</p>
		</statement>
		
	</exercise>

	<todo>Finish solution.</todo>

	<exercise number="2">
		<statement>
			<p>Demuestre que <m>{\mathbb Q }( \sqrt{2}\, )</m> es un espacio vectorial.</p>
		</statement>
		
	</exercise>

	<exercise number="3">
		<statement>
			<p>Sea <m>{\mathbb Q }( \sqrt{2}, \sqrt{3}\, )</m> el cuerpo de los elementos de la forma <m>a + b \sqrt{2}  + c \sqrt{3} + d \sqrt{6}</m>, donde <m>a, b, c, d</m> están en <m>{\mathbb Q}</m>. Demuestre que <m>{\mathbb Q }( \sqrt{2}, \sqrt{3}\, )</m> es un espacio vectorial de dimensión 4 sobre <m>{\mathbb Q}</m>.  Encuentre una base para <m>{\mathbb Q }( \sqrt{2}, \sqrt{3}\, )</m>.</p>
		</statement>
		<hint>
			<p><m>{\mathbb Q}(\sqrt{2}, \sqrt{3}\, )</m> tiene base <m>\{ 1, \sqrt{2}, \sqrt{3}, \sqrt{6}\, \}</m>  sobre <m>{\mathbb Q}</m>.</p>
		</hint>
		
	</exercise>

	<todo>Finish solution.</todo>

	<exercise number="4">
		<statement>
			<p>Demuestre que los números complejos forman un espacio vectorial de dimensión 2 sobre <m>{\mathbb R}</m>.</p>
		</statement>
		
	</exercise>

	<exercise number="5">
		<statement>
			<p>Demuestre que el conjunto <m>P_n</m> de todos los polinomios de grado menor a <m>n</m> forma un subespacio del espacio vectorial <m>F[x]</m>. Encuentre una base para <m>P_n</m> y calcule la dimensión de  <m>P_n</m>.</p>
		</statement>
		<hint>
			<p>El conjunto <m>\{ 1, x, x^2, \ldots, x^{n-1} \}</m> es una base para <m>P_n</m>.</p>
		</hint>
		
	</exercise>

	<todo>Finish solution.</todo>

	<exercise number="6">
		<statement>
			<p>Sea <m>F</m> un cuerpo y denote por <m>F^n</m> al conjunto de las <m>n</m>-tuplas de elementos de <m>F</m>. Dados los vectores <m>u = (u_1, \ldots, u_n)</m> y <m>v = (v_1, \ldots, v_n)</m> en <m>F^n</m> y <m>\alpha</m> en <m>F</m>, defina la adición de vectores como
				<me>u + v = (u_1, \ldots, u_n) + (v_1, \ldots, v_n) = (u_1 + v_1, \ldots, u_n + v_n)</me>
			y el producto por escalar como
				<me>\alpha u = \alpha(u_1, \ldots, u_n)= (\alpha u_1, \ldots, \alpha u_n).</me>
			Demuestre que <m>F^n</m> es un espacio vectorial de dimensión <m>n</m> bajo estas operaciones.</p>
		</statement>
		
	</exercise>

	<todo>Finish solution.</todo>

	<exercise number="7">
		<statement>
			<p>Cuáles de los siguientes conjuntos son subespacios de <m>{\mathbb R}^3</m>? En caso de que el conjunto sea un subespacio, encuentre una base y calcule la dimensión.
				<ol>

					<li><p><m>\{ (x_1, x_2, x_3) : 3 x_1 - 2 x_2 + x_3 = 0 \}</m></p></li>

					<li><p><m>\{ (x_1, x_2, x_3) : 3 x_1 + 4 x_3 = 0, 2 x_1 - x_2 + x_3 = 0 \}</m></p></li>

					<li><p><m>\{ (x_1, x_2, x_3) : x_1 - 2 x_2 + 2 x_3 = 2 \}</m></p></li>

					<li><p><m>\{ (x_1, x_2, x_3) : 3 x_1 - 2 x_2^2 = 0 \}</m></p></li>

				</ol></p>
		</statement>
		<hint>
			<p>(a) Subespacio de dimensión 2 con base <m>\{(1, 0, -3), (0, 1, 2) \}</m>; (d) no es un subespacio</p>
		</hint>
		
	</exercise>

	<exercise number="8">
		<statement>
			<p>Muestre que el conjunto de todas las posibles soluciones <m>(x, y, z) \in {\mathbb R}^3</m> de las ecuaciones
				<md>
					<mrow>Ax + B y + C z &amp; =  0</mrow>
					<mrow>D x + E y + C z &amp; =  0</mrow>
				</md>
			forma un subespacio de <m>{\mathbb R}^3</m>.</p>
		</statement>
		
	</exercise>

	<exercise number="9">
		<statement>
			<p>Sea <m>W</m> el subconjunto de las funciones continuas definidas en <m>[0, 1]</m> tales que <m>f(0) = 0</m>.  Demuestre que <m>W</m> es un subespacio de <m>C[0, 1]</m>.</p>
		</statement>
		
	</exercise>

	<exercise number="10">
		<statement>
			<p>Sea <m>V</m> un espacio vectorial sobre <m>F</m>. Demuestre que <m>-(\alpha v) = (-\alpha)v = \alpha(-v)</m> para todo <m>\alpha \in F</m> y todo <m>v \in V</m>.</p>
		</statement>
		<hint>
			<p>Como <m>0 =  \alpha 0 = \alpha(-v + v) = \alpha(-v) + \alpha v</m>, se concluye que <m>- \alpha v = \alpha(-v)</m>.</p>
		</hint>
		
	</exercise>

	<exercise number="11">
		<statement>
			<p>Sea <m>V</m> un espacio vectorial de dimensión <m>n</m>. Demuestre cada uno de los siguientes enunciados.
				<ol>

					<li><p>Si <m>S = \{v_1, \ldots, v_n \}</m> es un conjunto linealmente independiente de vectores en <m>V</m>, entonces <m>S</m> es una base para <m>V</m>.</p></li>

					<li><p>Si <m>S = \{v_1, \ldots, v_n \}</m> genera <m>V</m>, entonces <m>S</m> es una base para <m>V</m>.</p></li>

					<li><p>Si <m>S = \{v_1, \ldots, v_k \}</m> es un conjunto linealmente independiente de vectores en <m>V</m> con <m>k \lt n</m>, entonces existen vectores <m>v_{k + 1}, \ldots, v_n</m> tales que
						<me>\{v_1, \ldots, v_k, v_{k + 1}, \ldots, v_n \}</me> 
					es una base para <m>V</m>.</p></li>

				</ol></p>
		</statement>
		
	</exercise>

	<exercise number="12">
		<statement>
			<p>Demuestre que cualquier conjunto de vectores que contenga a <m>{\mathbf 0}</m> es lineamente dependiente.</p>
		</statement>
		<hint>
			<p>Sea <m>v_0 = 0, v_1, \ldots, v_n \in V</m> y <m>\alpha_0 \neq 0, \alpha_1, \ldots, \alpha_n \in F</m>. Entonces <m>\alpha_0 v_0 + \cdots + \alpha_n v_n = 0</m>.</p>
		</hint>
		
	</exercise>

	<exercise number="13">
		<statement>
			<p>Sea <m>V</m> un espacio vectorial. Muestre que <m>\{ {\mathbf 0} \}</m> es un subespacio de <m>V</m> de dimensión cero.</p>
		</statement>
		
	</exercise>

	<exercise number="14">
		<statement>
			<p>Si un espacio vectorial <m>V</m> es generado por <m>n</m> vectores, cualquier conjunto de <m>m</m> vectores en <m>V</m>, con <m>m \gt n</m>, es linealmente dependiente.</p>
		</statement>
		
	</exercise>

	<exercise number="15" xml:id="exercise-vect-linear-transformation">
		<title>Transformaciones Lineales</title>
		<statement>
			<p>Sean <m>V</m> y <m>W</m> espacio s vectoriales sobre un cuerpo <m>F</m>, de dimensiones <m>m</m> y <m>n</m>, respectivamente. Si <m>T: V \rightarrow W</m> es una función que satisface
				<md>
					<mrow>T( u+ v ) &amp; =  T(u ) + T(v)</mrow>
					<mrow>T( \alpha v ) &amp; =  \alpha T(v)</mrow>
				</md>
			para todo <m>\alpha \in F</m> y para todo <m>u, v \in V</m>, entonces <m>T</m> es una <term>transformación lineal</term> de <m>V</m> en <m>W</m>. 
				<ol>

					<li><p>Demuestre que el <term>núcleo</term> de <m>T</m>, <m>\ker(T) = \{ v \in V : T(v) = {\mathbf 0} \}</m>, es un subespacio de <m>V</m>. El núcleo de <m>T</m> también se llama <term>espacio nulo</term> de <m>T</m>.</p></li>

					<li><p>Demuestre que el <term>rango</term> o <term>imagen</term> de <m>T</m>, <m>R(V) = \{ w \in W : T(v) = w \text{ for some } v \in V \}</m>, es un subespacio de <m>W</m>.</p></li>

					<li><p>Muestre que <m>T : V \rightarrow W</m> es inyectiva si y solo si <m>\ker(T) = \{ \mathbf 0 \}</m>.</p></li>

					<li><p>Sea <m>\{ v_1, \ldots, v_k \}</m> una base para el espacio nulo de <m>T</m>. Podemos extender esta base a una base <m>\{ v_1, \ldots, v_k, v_{k + 1}, \ldots, v_m\}</m> de <m>V</m>. ¿Por qué?  Demuestre que <m>\{ T(v_{k + 1}), \ldots, T(v_m) \}</m> es una base para el rango de <m>T</m>. Concluya que el rango de <m>T</m> tiene dimensión <m>m-k</m>.</p></li>

					<li><p>Supongamos que <m>\dim V = \dim W</m>.  Muestre que una transformación lineal <m>T : V \rightarrow W</m> es inyectiva si y solo si es epiyectiva.</p></li>

				</ol></p>
		</statement>
		<hint>
			<p>(a) Sean <m>u, v \in \ker(T)</m> y <m>\alpha \in F</m>.  Entonces
					<md>
						<mrow>T(u +v) = T(u) + T(v) = 0</mrow>
						<mrow>T(\alpha v) = \alpha T(v) = \alpha 0 = 0.</mrow>
					</md>
				Luego, <m>u + v, \alpha v \in \ker(T)</m>, y <m>\ker(T)</m> es un subespacio de <m>V</m>.</p>

			<p>(c)  <m>T(u) = T(v)</m> es equivalente a <m>T(u-v) = T(u) - T(v) = 0</m>, lo que se cumple si y solo si <m>u-v = 0</m>, es decir  <m>u = v</m>.</p>
		</hint>
		
	</exercise>

	<exercise number="16">
		<statement>
			<p>Sean <m>V</m> y <m>W</m> espacio vectoriales de dimensión finita <m>n</m> sobre un cuerpo <m>F</m>. Supongamos que  <m>T: V \rightarrow W</m> es un isomorfismo de espacios vectoriales. Si <m>\{ v_1, \ldots, v_n \}</m> es una pase de <m>V</m>, muestre que <m>\{ T(v_1), \ldots, T(v_n) \}</m> es una base de <m>W</m>. Concluya que cualquier espacio vectorial sobre <m>F</m> de dimensión <m>n</m> es isomorfo a <m>F^n</m>.</p>
		</statement>
		
	</exercise>

	<exercise number="17">
		<title>Sumas Directas</title>
		<statement>
			<p>Sean <m>U</m> y <m>V</m> subespacios de un espacio vectorial <m>W</m>. La suma de <m>U</m> y <m>V</m>, denotada por <m>U + V</m>, está definida como el conjunto de todos los vectores de la forma <m>u + v</m>, con <m>u \in U</m> y <m>v \in V</m>. 
				<ol>

					<li><p>Demuestre que <m>U + V</m> y <m>U \cap V</m> son subespacios de  <m>W</m>.</p></li>

					<li><p>Si <m>U + V = W</m> y <m>U \cap V = {\mathbf 0}</m>, entonces se dice que <m>W</m> es la <term>suma directa.</term>  En este caso, escribimos <m>W = U \oplus V</m>. <notation><usage>U \oplus V</usage><description>suma directa de espacios vectoriales <m>U</m> y <m>V</m></description></notation> Muestre que cada <m>w \in W</m> se puede escribir de forma única como <m>w = u + v</m>, donde <m>u \in U</m> y <m>v \in V</m>.</p></li>

					<li><p>Sea <m>U</m> un subespacio de dimensión <m>k</m> de un espacio vectorial <m>W</m> de dimensión <m>n</m>. Demuestre que existe un subespacio <m>V</m> de dimensión <m>n-k</m> tal que <m>W = U \oplus V</m>.  ¿Es único el subespacio <m>V</m>?</p></li>

					<li><p>Si <m>U</m> y <m>V</m> sin subespacios arbitrarios de un espacio vectorial <m>W</m>, muestre que
					<me>\dim( U + V) = \dim U + \dim V - \dim( U \cap V).</me></p></li>

				</ol></p>
		</statement>
		<hint>
			<p>(a) Sean <m>u, u' \in U</m> y sean <m>v, v' \in V</m>. Entonces
				<md>
					<mrow>(u + v) + (u' + v') &amp; = (u + u') + (v + v') \in U + V</mrow>
					<mrow>\alpha(u + v) &amp; = \alpha u + \alpha v \in U + V.</mrow>
				</md></p>
			</hint>
		
	</exercise>

	<exercise number="18">
		<title>Espacios Duales</title>
		<statement>
			<p>Sean <m>V</m> y <m>W</m> espacios vectoriales de dimensión finita sobre un cuerpo <m>F</m>. 
				<ol>

					<li><p>Muestre que el conjunto de todas las transformaciones lineales de <m>V</m> en <m>W</m>, denotado por <m>\Hom(V, W)</m>, es un espacio vectorial sobre <m>F</m>, donde definimos la adición de vectores como sigue: <notation><usage>\Hom(V, W)</usage><description>conjunto de todas las transformaciones lineales de  <m>U</m> en <m>V</m></description></notation>
						<md>
							<mrow>(S + T)(v) &amp; =  S(v) +T(v)</mrow>
							<mrow>(\alpha S)(v) &amp; =  \alpha S(v),</mrow>
						</md>
					donde <m>S, T \in \Hom(V, W)</m>, <m>\alpha \in F</m>, y <m>v \in V</m>.</p></li>
			 
					<li><p>Sea <m>V</m> un <m>F</m>-espacio vectorial. Se define el <term>espacio dual</term> de <m>V</m> como <m>V^* = \Hom(V, F)</m>. <notation><usage>V^*</usage><description>dual de un espacio vectorial <m>V</m></description></notation> Los elementos en el dual de un espacio <m>V</m> se llaman <term>funcionales lineales.</term>  Sea <m>v_1, \ldots, v_n</m> una base ordenada para <m>V</m>. Si <m>v = \alpha_1 v_1 + \cdots + \alpha_n v_n</m> es cualquier vector en <m>V</m>, definimos un funcional lineal <m>\phi_i : V \rightarrow F</m> como <m>\phi_i (v) = \alpha_i</m>. Muestre que los <m>\phi_i</m> forman una base de <m>V^*</m>. Esta base se denomina <term>base dual</term> de <m>v_1, \ldots, v_n</m> (o simplemente la base dual si el contexto deja claro el significado).</p></li>
			 
					<li><p>Considere la base <m>\{ (3, 1), (2, -2) \}</m> de <m>{\mathbb R}^2</m>. ¿Cuál es la base dual de <m>({\mathbb R}^2)^*</m>?</p></li>

					<li><p>Sea <m>V</m> un espacio vectorial de dimensión <m>n</m> sobre un cuerpo <m>F</m> y sea  <m>V^{* *}</m> el espacio dual de <m>V^*</m>. Muestre que cada elemento <m>v \in V</m> define un elemento <m>\lambda_v</m> en <m>V^{**}</m> y que la función <m>v \mapsto \lambda_v</m> es un isomorfismo de  <m>V</m> con <m>V^{**}</m>.</p></li>

			</ol></p>
		</statement>
		
	</exercise>

</exercises>
